pwcheck/__init__.py
pwcheck/checker.py
pwcheck/constants.py
pwcheck/generate.py
pwcheck/lib.py
pwcheck-0.3.1.dist-info/LICENSE
pwcheck-0.3.1.dist-info/WHEEL
pwcheck-0.3.1.dist-info/METADATA
pwcheck-0.3.1.dist-info/RECORD
