Metadata-Version: 2.1
Name: pwcheck
Version: 0.3.1
Summary: Python Password Checker
Home-page: https://github.com/Itotutona/pwcheck
License: GNU
Author: Itotutona
Author-email: itotutona.github@evta.fr
Requires-Python: >=3.9,<4.0
Classifier: License :: Other/Proprietary License
Classifier: Programming Language :: Python :: 3
Classifier: Programming Language :: Python :: 3.9
Project-URL: Documentation, https://github.com/Itotutona/pwcheck/tree/master/docs
Project-URL: Repository, https://github.com/Itotutona/pwcheck
